terminal_in_colors/ColorTerminal.py
terminal_in_colors/__init__.py
terminal_in_colors/info_colors.py
terminal_in_colors-0.1.3.dist-info/LICENSE
terminal_in_colors-0.1.3.dist-info/METADATA
terminal_in_colors-0.1.3.dist-info/WHEEL
terminal_in_colors-0.1.3.dist-info/RECORD
