Metadata-Version: 2.1
Name: terminal-in-colors
Version: 0.1.3
Summary: Your terminal in colors :D
Home-page: https://github.com/kurotom/terminal-in-colors.git
License: LGPL-3.0-or-later
Keywords: colors,terminal,color,console
Author: kurotom
Author-email: 55354389+kurotom@users.noreply.github.com
Requires-Python: >=3.7,<4.0
Classifier: License :: OSI Approved :: GNU Lesser General Public License v3 or later (LGPLv3+)
Classifier: Programming Language :: Python :: 3
Classifier: Programming Language :: Python :: 3.7
Classifier: Programming Language :: Python :: 3.8
Classifier: Programming Language :: Python :: 3.9
Classifier: Programming Language :: Python :: 3.10
Classifier: Programming Language :: Python :: 3.11
Classifier: Topic :: Terminals
Project-URL: Bug Tracker, https://github.com/kurotom/terminal-in-colors/issues
Project-URL: Documentation, https://kurotom.github.io/terminal_in_colors/
Project-URL: Repository, https://github.com/kurotom/terminal-in-colors.git
